drmatlantis/__init__.py
drmatlantis-2.0.dist-info/METADATA
drmatlantis-2.0.dist-info/WHEEL
drmatlantis-2.0.dist-info/top_level.txt
drmatlantis-2.0.dist-info/RECORD
