Metadata-Version: 2.1
Name: drmatlantis
Version: 2.0
Summary: Dr. MATLANTIS server tool that connects local chatbot to MATLANTIS server
Author: Hristo Todorov
Author-email: httodoroff@gmail.com
License: MIT
Requires-Dist: anywidget
Requires-Dist: traitlets
Requires-Dist: ipylab
Requires-Dist: IPython
Requires-Dist: traceback
Requires-Dist: json
